{
    "product": [
      {
        "name": "Парикмахерское кресло «Норм» гидравлическое",
        "img": "http://dev-wbooster.ru/test_task/img/img-1.png",
        "price": "9901"
      },
      {
        "name": "Парикмахерское кресло «Норм» гидравлическое",
        "img": "http://dev-wbooster.ru/test_task/img/img-1.png",
        "price": "9902"
      },
      {
        "name": "Парикмахерское кресло «Норм» гидравлическое",
        "img": "http://dev-wbooster.ru/test_task/img/img-1.png",
        "price": "9903"
      },
      {
        "name": "Парикмахерское кресло «Норм» гидравлическое",
        "img": "http://dev-wbooster.ru/test_task/img/img-1.png",
        "price": "9904"
      },
      {
        "name": "Парикмахерское кресло «Норм» гидравлическое",
        "img": "http://dev-wbooster.ru/test_task/img/img-1.png",
        "price": "9905"
      },
      {
        "name": "Парикмахерское кресло «Норм» гидравлическое",
        "img": "http://dev-wbooster.ru/test_task/img/img-1.png",
        "price": "9906"
      }
    ]
  }